footballAPIClient/__init__.py
footballAPIClient/__main__.py
footballAPIClient/_constants.py
footballAPIClient/Exceptions/ApiKeyMissingError.py
footballAPIClient/Exceptions/APILimitExceededError.py
footballAPIClient/Exceptions/InternalApiException.py
footballAPIClient/Exceptions/MissingParametersError.py
footballAPIClient/footballAPI.py
footballAPIClient/helpers/ParameterValidator.py
footballapiclient-0.0.4.dist-info/LICENSE
footballapiclient-0.0.4.dist-info/METADATA
footballapiclient-0.0.4.dist-info/WHEEL
footballapiclient-0.0.4.dist-info/RECORD
