Metadata-Version: 2.1
Name: footballapiclient
Version: 0.0.4
Summary: Python Binding (API wrapper) for the Football API.
Author: Rishav Ganguly
Author-email: rishav.ganguly07@gmail.com
Requires-Python: >=3.7,<4.0
Classifier: Development Status :: 4 - Beta
Classifier: License :: OSI Approved :: MIT License
Classifier: Operating System :: OS Independent
Classifier: Programming Language :: Python :: 3
Classifier: Programming Language :: Python :: 3.7
Classifier: Programming Language :: Python :: 3.8
Classifier: Programming Language :: Python :: 3.9
Classifier: Programming Language :: Python :: 3.10
Classifier: Programming Language :: Python :: 3.11
Requires-Dist: pycountry (>=22.3.5,<23.0.0)
Requires-Dist: requests (>=2.27.0,<3.0.0)
